{
  "db": {
    "name": "db",
    "connector": "memory"
  },
  "glamme": {
    "host": "54.180.179.66",
    "port": 36102,
    "database": "admin",
    "username": "master",
    "password": "HLc8X6H32M1hZGCk8wsAn3e",
    "name": "glamme",
    "connector": "mongodb"
  },
  "storage": {
    "name": "storage",
    "connector": "loopback-component-storage",
    "provider": "filesystem",
    "root": "./storage",
    "maxFileSize": "5000000000",
    "nameConflict": "makeUnique"
  },
  "storage_s3": {
    "name": "storage_s3",
    "connector": "loopback-component-storage",
    "provider": "amazon",
    "keyId": "AKIAYCWMDJKKWRSZVHF5",
    "key": "aFlTsU14UlzjQ59jbu67TcjJL6K06xyuI7kaj+nK",
    "acl": "public-read"
  },
  "myEmailDataSource": {
    "name": "myEmailDataSource",
    "connector": "mail",
    "transports": [
      {
        "type": "smtp",
        "host": "smtp.private.com",
        "secure": false,
        "port": 587,
        "tls": {
          "rejectUnauthorized": false
        },
        "auth": {
          "user": "me@private.com",
          "pass": "password"
        }
      }
    ]
  }
}
